MANIFEST.in
install_requires.txt
setup.py
ansible_terraform_variables/__init__.py
ansible_terraform_variables/ansible_terraform_variables.py
ansible_terraform_variables.egg-info/PKG-INFO
ansible_terraform_variables.egg-info/SOURCES.txt
ansible_terraform_variables.egg-info/dependency_links.txt
ansible_terraform_variables.egg-info/top_level.txt